cicero_sdk/__init__.py
cicero_sdk/router.py
cicero_sdk/rpc_client.py
cicero_sdk/sophia.py
cicero_sdk-0.1.0.dist-info/METADATA
cicero_sdk-0.1.0.dist-info/WHEEL
cicero_sdk-0.1.0.dist-info/licenses/LICENSE
cicero_sdk-0.1.0.dist-info/RECORD
