Metadata-Version: 2.4
Name: cicero-sdk
Version: 0.1.0
Summary: A Python SDK for Cicero RPC interactions
Project-URL: Homepage, https://cicero.sh
Project-URL: Issues, https://github.com/cicero-ai/sdk/issues
Author-email: Aquila Labs <matt@cicero.sh>
License-File: LICENSE
Classifier: License :: OSI Approved :: MIT License
Classifier: Operating System :: OS Independent
Classifier: Programming Language :: Python :: 3
Requires-Python: >=3.7
Requires-Dist: requests>=2.28.0
